cmake_common-5.1.data/data/share/cmake/common.cmake
cmake_common-5.1.data/scripts/ctest-driver.py
cmake_common-5.1.data/scripts/project-clang-format.py
cmake_common-5.1.dist-info/licenses/LICENSE.txt
project/__init__.py
project/build.py
project/configuration.py
project/linkage.py
project/mingw.py
project/os.py
project/platform.py
project/toolset.py
project/utils.py
project/version.py
project/boost/__init__.py
project/boost/archive.py
project/boost/build.py
project/boost/directory.py
project/boost/download.py
project/boost/version.py
cmake_common-5.1.dist-info/METADATA
cmake_common-5.1.dist-info/WHEEL
cmake_common-5.1.dist-info/entry_points.txt
cmake_common-5.1.dist-info/top_level.txt
cmake_common-5.1.dist-info/RECORD
