Metadata-Version: 2.4
Name: cmake_common
Version: 5.1
Summary: Utilities to help develop C++/CMake projects
Author-email: Egor Tensin <Egor.Tensin@gmail.com>
License: MIT
Project-URL: Homepage, https://github.com/egor-tensin/cmake-common
Project-URL: Bug Tracker, https://github.com/egor-tensin/cmake-common/issues
Classifier: Development Status :: 4 - Beta
Classifier: Intended Audience :: Developers
Classifier: License :: OSI Approved :: MIT License
Classifier: Programming Language :: C++
Classifier: Topic :: Software Development :: Build Tools
Requires-Python: >=3.6
License-File: LICENSE.txt
Requires-Dist: importlib-metadata~=4.0; python_version < "3.8"
Dynamic: license-file
